invisibles/__init__.py
invisibles/proxy.py
invisibles-0.1.0.dist-info/METADATA
invisibles-0.1.0.dist-info/WHEEL
invisibles-0.1.0.dist-info/licenses/LICENSE
invisibles-0.1.0.dist-info/RECORD
