Metadata-Version: 2.4
Name: invisibles
Version: 0.1.0
Summary: A modern Python library for transparent object proxying
License-File: LICENSE
Author: Gor Arakelyan
Author-email: gorarkln@gmail.com
Requires-Python: >=3.12,<4.0
Classifier: Programming Language :: Python :: 3
Classifier: Programming Language :: Python :: 3.12
Classifier: Programming Language :: Python :: 3.13
Classifier: Programming Language :: Python :: 3.14
